{
  "project_info": {
    "project_number": "747908259618",
    "project_id": "world-seg",
    "storage_bucket": "world-seg.appspot.com"
  },
  "client": [
    {
      "client_info": {
        "mobilesdk_app_id": "1:747908259618:android:30d0a1dd2ad5bd552e8f7b",
        "android_client_info": {
          "package_name": "com.worldseg.wmwsv2"
        }
      },
      "oauth_client": [],
      "api_key": [
        {
          "current_key": "AIzaSyDU1bcxufLnbo8OsjnC2EXRgcbKMcPF00g"
        }
      ],
      "services": {
        "appinvite_service": {
          "other_platform_oauth_client": []
        }
      }
    }
  ],
  "configuration_version": "1"
}